pretty_text/__init__.py
pretty_text/pretty.py
pretty_text-0.1.2.dist-info/WHEEL
pretty_text-0.1.2.dist-info/METADATA
pretty_text-0.1.2.dist-info/RECORD
